tabulate_rs/__init__.py
tabulate_rs/tabulate_rs.cpython-39-x86_64-linux-gnu.so
tabulate_rs-0.1.1.dist-info/METADATA
tabulate_rs-0.1.1.dist-info/WHEEL
tabulate_rs-0.1.1.dist-info/RECORD
